bizlogic/__init__.py
bizlogic/application.py
bizlogic/loan/__init__.py
bizlogic/loan/reader.py
bizlogic/loan/repayment.py
bizlogic/loan/status.py
bizlogic/loan/writer.py
bizlogic/protoc/__init__.py
bizlogic/protoc/loan_application_pb2.py
bizlogic/protoc/loan_pb2.py
bizlogic/protoc/vouch_pb2.py
bizlogic/utils.py
bizlogic/vouch.py
bizlogic-0.2.20.dist-info/LICENSE
bizlogic-0.2.20.dist-info/METADATA
bizlogic-0.2.20.dist-info/WHEEL
bizlogic-0.2.20.dist-info/RECORD
